grAPI/__init__.py
grAPI/cli.py
grAPI/core.py
grapix-0.1.2.dist-info/licenses/LICENSE
grapix-0.1.2.dist-info/METADATA
grapix-0.1.2.dist-info/WHEEL
grapix-0.1.2.dist-info/entry_points.txt
grapix-0.1.2.dist-info/top_level.txt
grapix-0.1.2.dist-info/RECORD
