Metadata-Version: 2.4
Name: grapix
Version: 0.1.2
Summary: An automated GraphQL/API endpoint extractor using Playwright.
Author-email: iPsalmy <ipsalmydghost@gmail.com>
License: MIT License
Requires-Python: >=3.8
License-File: LICENSE
Requires-Dist: playwright>=1.43.0
Dynamic: license-file
